gittle/__init__.py
gittle/server.py
gittle/exceptions.py
gittle/gittle.py
gittle/auth.py
gittle/utils/__init__.py
gittle/utils/urls.py
gittle/utils/paths.py
gittle/utils/git.py
gittle3-0.6.0.dist-info/METADATA
gittle3-0.6.0.dist-info/metadata.json
gittle3-0.6.0.dist-info/DESCRIPTION.rst
gittle3-0.6.0.dist-info/RECORD
gittle3-0.6.0.dist-info/top_level.txt
gittle3-0.6.0.dist-info/WHEEL
