Metadata-Version: 2.0
Name: gittle3
Version: 0.6.0
Summary: A high level pure python git implementation for Python 3
Home-page: https://github.com/powellc/gittle
Author: Aaron O'Mullan
Author-email: aaron@friendco.de
License: MIT
Keywords: git dulwich pure python gittle
Platform: UNKNOWN
Requires-Dist: paramiko (>=1.10.0)
Requires-Dist: pycrypto (==2.6)
Requires-Dist: dulwich (>=0.9.7)
Requires-Dist: funky (>=0.0.2)
